[
  {
    "roomName": "Captain's Quest Quarters",
    "hitCount": 612,
    "avgUserRatio": 2.06,
    "activeUsers": 34
  },
  {
    "roomName": "Monorail Station",
    "hitCount": 447,
    "avgUserRatio": 2.45,
    "activeUsers": 21
  },
  {
    "roomName": "Central Plaza",
    "hitCount": 244,
    "avgUserRatio": 1.43,
    "activeUsers": 17
  },
  {
    "roomName": "VMK Esplanade",
    "hitCount": 68,
    "avgUserRatio": 1.29,
    "activeUsers": 27
  },
  {
    "roomName": "Pirate Treehouse",
    "hitCount": 48,
    "avgUserRatio": 1.89,
    "activeUsers": 12
  },
  {
    "roomName": "Gallery",
    "hitCount": 44,
    "avgUserRatio": 1.25,
    "activeUsers": 17
  },
  {
    "roomName": "Pixar Pier Entrance",
    "hitCount": 32,
    "avgUserRatio": 1.08,
    "activeUsers": 15
  },
  {
    "roomName": "Discovery Island",
    "hitCount": 25,
    "avgUserRatio": 3.49,
    "activeUsers": 5
  },
  {
    "roomName": "Autopia Off Road on Mars",
    "hitCount": 23,
    "avgUserRatio": 1.31,
    "activeUsers": 11
  },
  {
    "roomName": "Castle Forecourt",
    "hitCount": 22,
    "avgUserRatio": 2.03,
    "activeUsers": 9
  },
  {
    "roomName": "Town Square",
    "hitCount": 17,
    "avgUserRatio": 1.06,
    "activeUsers": 14
  },
  {
    "roomName": "Dungeon",
    "hitCount": 17,
    "avgUserRatio": 1.32,
    "activeUsers": 11
  },
  {
    "roomName": "WS - Mexico",
    "hitCount": 17,
    "avgUserRatio": 1.04,
    "activeUsers": 5
  },
  {
    "roomName": "Main Street",
    "hitCount": 12,
    "avgUserRatio": 1.71,
    "activeUsers": 7
  },
  {
    "roomName": "Matterhorn",
    "hitCount": 11,
    "avgUserRatio": 1.02,
    "activeUsers": 9
  },
  {
    "roomName": "Monorail Train",
    "hitCount": 11,
    "avgUserRatio": 0.83,
    "activeUsers": 5
  },
  {
    "roomName": "Spell Room",
    "hitCount": 10,
    "avgUserRatio": 1.29,
    "activeUsers": 7
  },
  {
    "roomName": "Jungle Cruise Dock",
    "hitCount": 9,
    "avgUserRatio": 1.5,
    "activeUsers": 6
  },
  {
    "roomName": "Blue Bayou",
    "hitCount": 8,
    "avgUserRatio": 1.6,
    "activeUsers": 5
  },
  {
    "roomName": "Epcot Entrance",
    "hitCount": 8,
    "avgUserRatio": 0.79,
    "activeUsers": 4
  },
  {
    "roomName": "Shrunken Ned's Shop",
    "hitCount": 6,
    "avgUserRatio": 1.2,
    "activeUsers": 5
  },
  {
    "roomName": "Nautilus Grotto",
    "hitCount": 6,
    "avgUserRatio": 1.17,
    "activeUsers": 3
  },
  {
    "roomName": "Autopia Quest Track",
    "hitCount": 5,
    "avgUserRatio": 1.42,
    "activeUsers": 3
  },
  {
    "roomName": "Adventureland Bazaar",
    "hitCount": 5,
    "avgUserRatio": 0.88,
    "activeUsers": 4
  },
  {
    "roomName": "VMK Gallery",
    "hitCount": 5,
    "avgUserRatio": 0.9,
    "activeUsers": 5
  },
  {
    "roomName": "Castle Gardens",
    "hitCount": 4,
    "avgUserRatio": 0.67,
    "activeUsers": 6
  },
  {
    "roomName": "Lost Safari Party",
    "hitCount": 3,
    "avgUserRatio": 1.5,
    "activeUsers": 2
  },
  {
    "roomName": "WS - Norway",
    "hitCount": 3,
    "avgUserRatio": 1,
    "activeUsers": 3
  },
  {
    "roomName": "Shipwreck Graveyard",
    "hitCount": 2,
    "avgUserRatio": 1,
    "activeUsers": 2
  },
  {
    "roomName": "Storybookland",
    "hitCount": 2,
    "avgUserRatio": 0.67,
    "activeUsers": 3
  },
  {
    "roomName": "Fantasyland in The Sky",
    "hitCount": 2,
    "avgUserRatio": 1,
    "activeUsers": 2
  },
  {
    "roomName": "Banquet Hall",
    "hitCount": 2,
    "avgUserRatio": 1,
    "activeUsers": 2
  },
  {
    "roomName": "WS - United Kingdom",
    "hitCount": 1,
    "avgUserRatio": 0.5,
    "activeUsers": 2
  },
  {
    "roomName": "Everest Entrance",
    "hitCount": 1,
    "avgUserRatio": 0.5,
    "activeUsers": 2
  },
  {
    "roomName": "Forbidden Temple",
    "hitCount": 1,
    "avgUserRatio": 0.5,
    "activeUsers": 2
  },
  {
    "roomName": "Discovery Trading Company",
    "hitCount": 1,
    "avgUserRatio": 0.5,
    "activeUsers": 2
  }
]